devops_requests/__init__.py
devops_requests/grafana.py
devops_requests-0.0.2.dist-info/METADATA
devops_requests-0.0.2.dist-info/WHEEL
devops_requests-0.0.2.dist-info/top_level.txt
devops_requests-0.0.2.dist-info/RECORD
